waveletai/__init__.py
waveletai/_version.py
waveletai/app.py
waveletai/backend.py
waveletai/constants.py
waveletai/dataset.py
waveletai/envs.py
waveletai/exceptions.py
waveletai/experiment.py
waveletai/feature.py
waveletai/model.py
waveletai/run.py
waveletai/sessions.py
waveletai/backends/__init__.py
waveletai/backends/config.py
waveletai/backends/credentials.py
waveletai/backends/hosted_backend.py
waveletai/hardware/__init__.py
waveletai/hardware/constants.py
waveletai/mlflow_plugs/__init__.py
waveletai/mlflow_plugs/artifact_repository/__init__.py
waveletai/mlflow_plugs/artifact_repository/waveletai_artifact_repository.py
waveletai/mlflow_plugs/project_backend/__init__.py
waveletai/mlflow_plugs/project_backend/waveletai_backend.py
waveletai/mlflow_plugs/tracking_store/__init__.py
waveletai/mlflow_plugs/tracking_store/waveletai_store.py
waveletai/utils/__init__.py
waveletai/utils/async.py
waveletai/utils/datastream.py
waveletai/utils/storage_utils.py
waveletai-0.2.39.dist-info/LICENSE
waveletai-0.2.39.dist-info/METADATA
waveletai-0.2.39.dist-info/WHEEL
waveletai-0.2.39.dist-info/entry_points.txt
waveletai-0.2.39.dist-info/top_level.txt
waveletai-0.2.39.dist-info/RECORD
