Metadata-Version: 2.1
Name: waveletai
Version: 0.2.39
Summary: WaveletAI A Machine Learning Lifecycle Platform
Home-page: https://ai.xiaobodata.com/
Author: Janus
Project-URL: wavelet-plus, https://plus.xiaobodata.com/
Project-URL: wavelet-ai, https://ai.xiaobodata.com/
Keywords: ml ai waveletai
Classifier: Intended Audience :: Developers
Classifier: Development Status :: 4 - Beta
Classifier: Programming Language :: Python :: 3.7
Classifier: Natural Language :: Chinese (Simplified)
Classifier: Topic :: Scientific/Engineering :: Artificial Intelligence
Classifier: License :: OSI Approved :: GNU General Public License v3 or later (GPLv3+)
Requires-Python: >=3.6
License-File: LICENSE
Requires-Dist: pymysql
Requires-Dist: boto3
Requires-Dist: Minio
Requires-Dist: mlflow (<=1.29,>=1.27)
Requires-Dist: jsonschema (==3.2.0)
Requires-Dist: bravado
Requires-Dist: pika
Requires-Dist: tqdm
Requires-Dist: simplejson
Requires-Dist: future (>=0.17.1)
Requires-Dist: requests-oauthlib (>=1.0.0)
Requires-Dist: oauthlib (>=2.1.0)
Requires-Dist: protobuf (<=3.20.1)
